<?xml version="1.0" encoding="UTF-8" ?>
<beans xmlns="http://www.springframework.org/schema/beans"
       xmlns:xsi="http://www.w3.org/2001/XMLSchema-instance"
       xmlns:sec="http://www.springframework.org/schema/security"
       xsi:schemaLocation="
http://www.springframework.org/schema/security http://www.springframework.org/schema/security/spring-security.xsd
http://www.springframework.org/schema/beans http://www.springframework.org/schema/beans/spring-beans.xsd">

    <!-- Don't bother securing css and javascript resources -->
    <sec:http pattern="/js/**" security="none"/>
    <sec:http pattern="/css/**" security="none"/>
    <sec:http pattern="/fonts/**" security="none"/>

    <sec:http  request-matcher="regex" access-denied-page="/login.html?authorization_error=true">
        <sec:anonymous enabled="false"/>
        <sec:intercept-url pattern="/users.*" access="ROLE_USER"/>
        <sec:intercept-url pattern="/projects.*" access="ROLE_USER"/>

        <sec:form-login authentication-failure-url="/login.html?authentication_error=true" default-target-url="/"
                        login-page="/login.html" login-processing-url="/login"
                        password-parameter="password" username-parameter="username"/>
        <sec:logout logout-success-url="/" logout-url="/logout"/>
    </sec:http>

    <sec:authentication-manager alias="authenticationManager">
        <sec:authentication-provider user-service-ref="userService">
            <sec:password-encoder ref="passwordEncoder"/>
        </sec:authentication-provider>
    </sec:authentication-manager>
</beans>
